leony-0.11.98.dist-info/METADATA
leony-0.11.98.dist-info/WHEEL
leony-0.11.98.dist-info/license_files/LICENSE
leony/__init__.py
leony/leony.abi3.so
leony-0.11.98.dist-info/RECORD
