Metadata-Version: 2.3
Name: leony
Version: 0.11.98
Classifier: Programming Language :: Rust
Classifier: Programming Language :: Python :: Implementation :: CPython
Classifier: Programming Language :: Python :: Implementation :: PyPy
Requires-Dist: gevent ; extra == 'benchmark'
Requires-Dist: greenify ; extra == 'benchmark'
Requires-Dist: greenlet ; extra == 'benchmark'
Requires-Dist: boto3 ; extra == 'benchmark'
Requires-Dist: pydantic ; extra == 'benchmark'
Requires-Dist: boto3-stubs[essential] ; extra == 'benchmark'
Requires-Dist: pdoc ; extra == 'docs'
Requires-Dist: ruff ; extra == 'lint'
Requires-Dist: pytest ; extra == 'test'
Requires-Dist: python-dotenv ; extra == 'test'
Requires-Dist: pytest-asyncio ; extra == 'test'
Provides-Extra: benchmark
Provides-Extra: docs
Provides-Extra: lint
Provides-Extra: test
License-File: LICENSE
Summary: An fast asynchronous Python Http Client with TLS/JA3/JA4/HTTP2 fingerprint impersonate
License: Apache-2.0
Requires-Python: >=3.11, <3.13
